oss_ar/oss.py
oss_ar/sisa.py
oss_ar/sssalud.py
oss_ar/data/final-oss.json
oss_ar/data/sisa.csv
oss_ar/data/sisa.json
oss_ar/data/sss-1.tsv
oss_ar/data/sss-10.tsv
oss_ar/data/sss-11.tsv
oss_ar/data/sss-12.tsv
oss_ar/data/sss-13.tsv
oss_ar/data/sss-14.tsv
oss_ar/data/sss-15.tsv
oss_ar/data/sss-16.tsv
oss_ar/data/sss-17.tsv
oss_ar/data/sss-18.tsv
oss_ar/data/sss-19.tsv
oss_ar/data/sss-2.tsv
oss_ar/data/sss-3.tsv
oss_ar/data/sss-4.tsv
oss_ar/data/sss-5.tsv
oss_ar/data/sss-6.tsv
oss_ar/data/sss-7.tsv
oss_ar/data/sss-8.tsv
oss_ar/data/sss-9.tsv
oss_ar/data/sss.json
oss_ar-0.135.dist-info/METADATA
oss_ar-0.135.dist-info/WHEEL
oss_ar-0.135.dist-info/top_level.txt
oss_ar-0.135.dist-info/RECORD
