Metadata-Version: 2.4
Name: oss_ar
Version: 0.135
Summary: Lista de Obras Sociales Argentinas
Home-page: https://github.com/cluster311/obras-sociales-argentinas
Author: Andres Vazquez
Author-email: andres@data99.com.ar
License: MIT
Classifier: Programming Language :: Python :: 3
Classifier: Programming Language :: Python :: 3.6
Classifier: License :: OSI Approved :: MIT License
Classifier: Operating System :: OS Independent
Classifier: Intended Audience :: Developers
Requires-Python: >=3.6
Requires-Dist: requests>2
Dynamic: author
Dynamic: author-email
Dynamic: classifier
Dynamic: description
Dynamic: description-content-type
Dynamic: home-page
Dynamic: license
Dynamic: requires-dist
Dynamic: requires-python
Dynamic: summary
